Metadata-Version: 1.1
Name: muffin-peewee-async
Version: 0.1.1
Summary: Peewee integration to Muffin framework
Home-page: https://github.com/serathius/muffin-peewee-async
Author: Marek Siarkowicz
Author-email: serathius@protonmail.com
License: MIT
Keywords: muffin,peewee,peewee-async
Platform: Any
Classifier: Development Status :: 3 - Alpha
Classifier: Intended Audience :: Developers
Classifier: License :: OSI Approved :: MIT License
Classifier: Natural Language :: English
Classifier: Operating System :: OS Independent
Classifier: Programming Language :: Python
Classifier: Programming Language :: Python :: 3
Classifier: Programming Language :: Python :: 3.4
Classifier: Programming Language :: Python :: 3.5
Classifier: Programming Language :: Python :: 3.6
Classifier: Topic :: Utilities
Classifier: Topic :: Software Development :: Testing
Classifier: Topic :: Software Development :: Libraries :: Python Modules
